{
	"configurations" : 
	[
		{
			"directories" : 
			[
				{
					"build" : ".",
					"jsonFile" : "directory-.-Debug-f5ebdc15457944623624.json",
					"minimumCMakeVersion" : 
					{
						"string" : "3.28"
					},
					"projectIndex" : 0,
					"source" : ".",
					"targetIndexes" : 
					[
						0
					]
				}
			],
			"name" : "Debug",
			"projects" : 
			[
				{
					"directoryIndexes" : 
					[
						0
					],
					"name" : "ejercicio9",
					"targetIndexes" : 
					[
						0
					]
				}
			],
			"targets" : 
			[
				{
					"directoryIndex" : 0,
					"id" : "ejercicio9::@6890427a1f51a3e7e1df",
					"jsonFile" : "target-ejercicio9-Debug-d5cc685eb7ee64561c25.json",
					"name" : "ejercicio9",
					"projectIndex" : 0
				}
			]
		}
	],
	"kind" : "codemodel",
	"paths" : 
	{
		"build" : "/home/arielito/CLionProjects/Ejercicios/Arrays/ejercicio9/cmake-build-debug",
		"source" : "/home/arielito/CLionProjects/Ejercicios/Arrays/ejercicio9"
	},
	"version" : 
	{
		"major" : 2,
		"minor" : 6
	}
}
